intake_parquet/__init__.py
intake_parquet/_version.py
intake_parquet/source.py
intake_parquet-0.3.0.dist-info/LICENSE
intake_parquet-0.3.0.dist-info/METADATA
intake_parquet-0.3.0.dist-info/WHEEL
intake_parquet-0.3.0.dist-info/entry_points.txt
intake_parquet-0.3.0.dist-info/top_level.txt
intake_parquet-0.3.0.dist-info/RECORD
