Metadata-Version: 2.1
Name: intake-parquet
Version: 0.3.0
Summary: Intake parquet plugin
Home-page: https://github.com/ContinuumIO/intake-parquet
Maintainer: Martin Durant
Maintainer-email: martin.durant@utoronto.ca
License: BSD
License-File: LICENSE
Requires-Dist: intake
Requires-Dist: pandas
Requires-Dist: fastparquet
Requires-Dist: pyarrow
